{
  "version": "0.6.0",
  "description": "Terminal code review for AI coding agents",
  "homepage": "https://github.com/matheusfillipe/diffler",
  "license": "MIT OR Apache-2.0",
  "architecture": {
    "64bit": {
      "url": "https://github.com/matheusfillipe/diffler/releases/download/v0.6.0/diffler-v0.6.0-x86_64-pc-windows-msvc.zip",
      "hash": "3b477c384799ee1b0f9f49b7af860126e44ec9747943435f1e45ccade5664bf7",
      "extract_dir": "diffler-v0.6.0-x86_64-pc-windows-msvc"
    },
    "arm64": {
      "url": "https://github.com/matheusfillipe/diffler/releases/download/v0.6.0/diffler-v0.6.0-aarch64-pc-windows-msvc.zip",
      "hash": "1f31ce255acf2277c3585df94ec675eddd7a68f3b6c64e50fb426e8f1e53de73",
      "extract_dir": "diffler-v0.6.0-aarch64-pc-windows-msvc"
    }
  },
  "bin": "diffler.exe"
}
